vidinlp/__init__.py
vidinlp/data/chall_word_list.txt
vidinlp/data/lexicon.txt
vidinlp-1.1.5.2.dist-info/licenses/LICENSE.txt
vidinlp-1.1.5.2.dist-info/METADATA
vidinlp-1.1.5.2.dist-info/WHEEL
vidinlp-1.1.5.2.dist-info/top_level.txt
vidinlp-1.1.5.2.dist-info/RECORD
