Metadata-Version: 2.4
Name: vidinlp
Version: 1.1.5.2
Summary: NLP library for linguists built on top of spaCy, Scikit-Learn, and vadersentiment.
Home-page: https://github.com/vidito/vidinlp
Author: Vahid Niamadpour
Author-email: contact@pythonology.eu
Classifier: Programming Language :: Python :: 3
Classifier: License :: OSI Approved :: MIT License
Classifier: Operating System :: OS Independent
Requires-Python: >=3.9
License-File: LICENSE.txt
Requires-Dist: spacy>=3.0.0
Requires-Dist: scikit-learn>=0.24.0
Requires-Dist: pandas>=1.0.0
Requires-Dist: numpy>=1.19.0
Requires-Dist: vaderSentiment>=3.3.2
Dynamic: author
Dynamic: author-email
Dynamic: classifier
Dynamic: description
Dynamic: description-content-type
Dynamic: home-page
Dynamic: license-file
Dynamic: requires-dist
Dynamic: requires-python
Dynamic: summary
